{
	"configurations" : 
	[
		{
			"directories" : 
			[
				{
					"build" : ".",
					"jsonFile" : "directory-.-Debug-f5ebdc15457944623624.json",
					"minimumCMakeVersion" : 
					{
						"string" : "3.15"
					},
					"projectIndex" : 0,
					"source" : ".",
					"targetIndexes" : 
					[
						0
					]
				}
			],
			"name" : "Debug",
			"projects" : 
			[
				{
					"directoryIndexes" : 
					[
						0
					],
					"name" : "GraphicsStuff",
					"targetIndexes" : 
					[
						0
					]
				}
			],
			"targets" : 
			[
				{
					"directoryIndex" : 0,
					"id" : "GraphicsStuff::@6890427a1f51a3e7e1df",
					"jsonFile" : "target-GraphicsStuff-Debug-8cb4c19305f17a55d98d.json",
					"name" : "GraphicsStuff",
					"projectIndex" : 0
				}
			]
		}
	],
	"kind" : "codemodel",
	"paths" : 
	{
		"build" : "/home/hiatus/Documents/2DFluidSimulator/build",
		"source" : "/home/hiatus/Documents/2DFluidSimulator"
	},
	"version" : 
	{
		"major" : 2,
		"minor" : 7
	}
}
